py_altium365/__init__.py
py_altium365/altium_api.py
py_altium365/altium_api_workspace.py
py_altium365/base/__init__.py
py_altium365/base/connection_handler.py
py_altium365/base/enums.py
py_altium365/connection/__init__.py
py_altium365/connection/json_con.py
py_altium365/connection/json_con_search_async.py
py_altium365/connection/soapy_con.py
py_altium365/connection/soapy_con_portal.py
py_altium365/connection/soapy_con_service_discovery.py
py_altium365/connection/soapy_con_workspace.py
py_altium365/connection/vault/__init__.py
py_altium365/connection/vault/soapy_con_vault.py
py_altium365/connection/vault/soapy_con_vault_base.py
pyaltium365-0.5.1.post2.dist-info/METADATA
pyaltium365-0.5.1.post2.dist-info/WHEEL
pyaltium365-0.5.1.post2.dist-info/top_level.txt
pyaltium365-0.5.1.post2.dist-info/RECORD
