Metadata-Version: 2.4
Name: PyAltium365
Version: 0.5.1.post2
Summary: an library that can interface with altium 365
Author-email: Dylan Gybels <gybelsdylan@gmail.com>
License-Expression: MIT AND (Apache-2.0 OR BSD-2-Clause)
Project-URL: Homepage, https://github.com/krakdustten/PyAltium365
Keywords: altium,altium365,altium-365,altium-365-api,altium-365-api-python,altium-365-api-python-client
Classifier: Development Status :: 2 - Pre-Alpha
Classifier: Intended Audience :: Developers
Classifier: Programming Language :: Python :: 3
Classifier: Programming Language :: Python :: 3.9
Classifier: Programming Language :: Python :: 3.10
Classifier: Programming Language :: Python :: 3.11
Classifier: Programming Language :: Python :: 3.12
Classifier: Programming Language :: Python :: 3.13
Requires-Python: >=3.9
Requires-Dist: requests>=2
Requires-Dist: pydantic>=2.0.0
Requires-Dist: pydantic-xml>=2.14.0
